<?xml version="1.0" encoding="UTF-8"?>

<resource-action-mapping>
	<portlet-resource>
		<portlet-name>vdocmanage</portlet-name>
		<permissions>
			<supports>
				<action-key>ACCESS_IN_CONTROL_PANEL</action-key>
                <action-key>ADD_TO_PAGE</action-key>                
				<action-key>CONFIGURATION</action-key>
				<action-key>VIEW</action-key>
			</supports>
			<site-member-defaults>
                <action-key>VIEW</action-key>
            </site-member-defaults>
			<community-defaults>
				<action-key>VIEW</action-key>
			</community-defaults>
			<guest-defaults>
				<action-key>VIEW</action-key>
			</guest-defaults>
			<guest-unsupported>
				<action-key>ACCESS_IN_CONTROL_PANEL</action-key>				
				<action-key>CONFIGURATION</action-key>
			</guest-unsupported>
		</permissions>
	</portlet-resource>
	
	<model-resource>
		<model-name>com.portlet.vdoc.model.vdocDocument</model-name>
		<portlet-ref>
			<portlet-name>vdocmanage</portlet-name>
		</portlet-ref>
		<permissions>
			<supports>
				<action-key>ADD_DOCUMENT</action-key>
				<action-key>DELETE</action-key>
				<action-key>PERMISSIONS</action-key>
				<action-key>UPDATE</action-key>
				<action-key>VIEW</action-key>
			</supports>
			<community-defaults>
				<action-key>VIEW</action-key>
			</community-defaults>
			<guest-defaults>
				<action-key>VIEW</action-key>
			</guest-defaults>
			<guest-unsupported>
				<action-key>ADD_DOCUMENT</action-key>
				<action-key>DELETE</action-key>
				<action-key>PERMISSIONS</action-key>
				<action-key>UPDATE</action-key>
			</guest-unsupported>
		</permissions>
	</model-resource>
	
	<model-resource>
		<model-name>com.portlet.vdoc.model.vdocField</model-name>
		<portlet-ref>
			<portlet-name>vdocmanage</portlet-name>
		</portlet-ref>
		<permissions>
			<supports>
				<action-key>ADD_FIELD</action-key>
				<action-key>DELETE</action-key>
				<action-key>PERMISSIONS</action-key>
				<action-key>UPDATE</action-key>
				<action-key>VIEW</action-key>
			</supports>
			<community-defaults>
				<action-key>VIEW</action-key>
			</community-defaults>
			<guest-defaults>
				<action-key>VIEW</action-key>
			</guest-defaults>
			<guest-unsupported>
				<action-key>ADD_FIELD</action-key>
				<action-key>DELETE</action-key>
				<action-key>PERMISSIONS</action-key>
				<action-key>UPDATE</action-key>
			</guest-unsupported>
		</permissions>
	</model-resource>
	
	<model-resource>
		<model-name>com.portlet.vdoc.model.vdocOrg</model-name>
		<portlet-ref>
			<portlet-name>vdocmanage</portlet-name>
		</portlet-ref>
		<permissions>
			<supports>
				<action-key>ADD_ORG</action-key>
				<action-key>DELETE</action-key>
				<action-key>PERMISSIONS</action-key>
				<action-key>UPDATE</action-key>
				<action-key>VIEW</action-key>
			</supports>
			<community-defaults>
				<action-key>VIEW</action-key>
			</community-defaults>
			<guest-defaults>
				<action-key>VIEW</action-key>
			</guest-defaults>
			<guest-unsupported>
				<action-key>ADD_ORG</action-key>
				<action-key>DELETE</action-key>
				<action-key>PERMISSIONS</action-key>
				<action-key>UPDATE</action-key>
			</guest-unsupported>
		</permissions>
	</model-resource>
</resource-action-mapping>